mcp_server_dr/__init__.py
mcp_server_dr/__main__.py
mcp_server_dr/server.py
mcp_server_dr-0.1.0.dist-info/METADATA
mcp_server_dr-0.1.0.dist-info/WHEEL
mcp_server_dr-0.1.0.dist-info/entry_points.txt
mcp_server_dr-0.1.0.dist-info/top_level.txt
mcp_server_dr-0.1.0.dist-info/RECORD
