Metadata-Version: 2.4
Name: mcp-server-dr
Version: 0.1.0
Summary: MCP-Deepresearch-Server
Requires-Python: >=3.12
Requires-Dist: asyncio>=3.4.3
Requires-Dist: mcp>=1.7.1
Requires-Dist: openai>=1.77.0
Requires-Dist: openai-agents>=0.0.14
Requires-Dist: pydantic>=2.11.4
Requires-Dist: typing>=3.10.0.0
